grapes/__init__.py
grapes/context.py
grapes/core.py
grapes/design.py
grapes/evaluate.py
grapes/features.py
grapes/function_composer.py
grapes/merge.py
grapes/path.py
grapes/reachability.py
grapes/simplify.py
grapes/util.py
grapes/visualize.py
grapes-0.10.4.dist-info/METADATA
grapes-0.10.4.dist-info/WHEEL
grapes-0.10.4.dist-info/licenses/LICENSE.txt
grapes-0.10.4.dist-info/licenses/NOTICE.txt
grapes-0.10.4.dist-info/RECORD
