Metadata-Version: 2.4
Name: grapes
Version: 0.10.4
Summary: Helper for dataflow based programming
Project-URL: Homepage, https://github.com/giuliofoletto/grapes
Author-email: Giulio Foletto <giulio.foletto@outlook.com>
License-Expression: Apache-2.0
License-File: LICENSE.txt
License-File: NOTICE.txt
Requires-Dist: matplotlib
Requires-Dist: networkx
Requires-Dist: pygraphviz
Requires-Dist: tomli; python_version < '3.11'
Provides-Extra: testing
Requires-Dist: pytest; extra == 'testing'
